cz_custom_conventional_commits.py
cz_custom_conventional_commits-0.1.0.dist-info/METADATA
cz_custom_conventional_commits-0.1.0.dist-info/WHEEL
cz_custom_conventional_commits-0.1.0.dist-info/entry_points.txt
cz_custom_conventional_commits-0.1.0.dist-info/top_level.txt
cz_custom_conventional_commits-0.1.0.dist-info/RECORD
