Metadata-Version: 2.4
Name: cz-custom-conventional-commits
Version: 0.1.0
Summary: Add your description here
Requires-Python: >=3.10
Requires-Dist: commitizen
